rgb/Color.py
rgb/Palette.py
rgb/__init__.py
rgb/palettes.py
rgb/printer.py
rgb-0.0.3.dist-info/METADATA
rgb-0.0.3.dist-info/WHEEL
rgb-0.0.3.dist-info/top_level.txt
rgb-0.0.3.dist-info/RECORD
