Metadata-Version: 2.1
Name: rgb
Version: 0.0.3
Summary: Grab your palette!
Home-page: https://github.com/seungjaeryanlee/rgb
Author: Seungjae Ryan Lee
Author-email: seungjaeryanlee@gmail.com
License: UNKNOWN
Project-URL: Bug Tracker, https://github.com/seungjaeryanlee/rgb/issues
Platform: UNKNOWN
Classifier: Programming Language :: Python :: 3
Classifier: Operating System :: OS Independent
Requires-Python: >=3.6
